{
  "cookies": {
    "__uzmc": "4048368869606",
    "__uzmd": "1782890310"
  },
  "created_at": "2026-07-01T07:18:31.187250+00:00",
  "elapsed": 0.244457,
  "encoding": "utf-8",
  "expires": "2026-12-28T07:18:31.187223+00:00",
  "headers": {
    "Cache-Control": "no-cache",
    "Connection": "keep-alive",
    "Content-Encoding": "gzip",
    "Content-Type": "application/json",
    "Cross-Origin-Opener-Policy": "same-origin",
    "Date": "Wed, 01 Jul 2026 07:18:31 GMT",
    "Expires": "-1",
    "Pragma": "no-cache",
    "Set-Cookie": "__uzmc=4048368869606; HttpOnly; path=/; Expires=Wed, 30-Dec-26 07:18:30 GMT ; Max-Age=15724800; SameSite=Lax, __uzmd=1782890310; HttpOnly; path=/; Expires=Wed, 30-Dec-26 07:18:30 GMT ; Max-Age=15724800; SameSite=Lax",
    "Transfer-Encoding": "chunked",
    "Vary": "Accept-Encoding",
    "X-Azion-Edge-Location": "LAX",
    "X-Azion-Request-Id": "4ca0fac5fdc3c82c153865c2b314c00e",
    "X-Content-Type-Options": "nosniff",
    "X-Frame-Options": "deny",
    "X-XSS-Protection": "1; mode=block",
    "xS": "041"
  },
  "reason": "OK",
  "request": {
    "cookies": {
      "__uzma": "7fda7552-57cf-41dc-b647-273a043839e8",
      "__uzmb": "1782890255",
      "__uzme": "6599",
      "__uzmc": "3756168566826",
      "__uzmd": "1782890310"
    },
    "headers": {
      "Accept": "*/*",
      "Accept-Encoding": "gzip, deflate, zstd",
      "Connection": "keep-alive",
      "Cookie": "__uzma=7fda7552-57cf-41dc-b647-273a043839e8; __uzmb=1782890255; __uzme=6599; __uzmc=3756168566826; __uzmd=1782890310",
      "User-Agent": "python-requests/2.34.2"
    },
    "method": "GET",
    "url": "https://servicebus2.caixa.gov.br/portaldeloterias/api/timemania/233"
  },
  "status_code": 200,
  "url": "https://servicebus2.caixa.gov.br/portaldeloterias/api/timemania/233",
  "_decoded_content": {
    "acumulado": true,
    "dataApuracao": "03/08/2011",
    "dataProximoConcurso": "06/08/2011",
    "dezenasSorteadasOrdemSorteio": [
      "16",
      "41",
      "68",
      "78",
      "11",
      "56",
      "32"
    ],
    "exibirDetalhamentoPorCidade": true,
    "id": null,
    "indicadorConcursoEspecial": 1,
    "listaDezenas": [
      "11",
      "16",
      "32",
      "41",
      "56",
      "68",
      "78"
    ],
    "listaDezenasSegundoSorteio": null,
    "listaMunicipioUFGanhadores": [],
    "listaRateioPremio": [
      {
        "descricaoFaixa": "7 acertos",
        "faixa": 1,
        "numeroDeGanhadores": 0,
        "valorPremio": 0.0
      },
      {
        "descricaoFaixa": "6 acertos",
        "faixa": 2,
        "numeroDeGanhadores": 1,
        "valorPremio": 117311.56
      },
      {
        "descricaoFaixa": "5 acertos",
        "faixa": 3,
        "numeroDeGanhadores": 157,
        "valorPremio": 1067.43
      },
      {
        "descricaoFaixa": "4 acertos",
        "faixa": 4,
        "numeroDeGanhadores": 3210,
        "valorPremio": 6.0
      },
      {
        "descricaoFaixa": "3 acertos",
        "faixa": 5,
        "numeroDeGanhadores": 33694,
        "valorPremio": 2.0
      },
      {
        "descricaoFaixa": "Time do Cora\u00e7\u00e3o",
        "faixa": 6,
        "numeroDeGanhadores": 16876,
        "valorPremio": 5.0
      }
    ],
    "listaResultadoEquipeEsportiva": null,
    "localSorteio": "Caminh\u00e3o da Sorte",
    "nomeMunicipioUFSorteio": "POUSO ALEGRE, MG",
    "nomeTimeCoracaoMesSorte": "CEAR\u00c1/CE",
    "numero": 233,
    "numeroConcursoAnterior": 232,
    "numeroConcursoFinal_0_5": 235,
    "numeroConcursoProximo": 234,
    "numeroJogo": 20,
    "observacao": "",
    "premiacaoContingencia": null,
    "tipoJogo": "TIMEMANIA",
    "tipoPublicacao": 3,
    "ultimoConcurso": true,
    "valorArrecadado": 2193408.0,
    "valorAcumuladoConcurso_0_5": 254594.48,
    "valorAcumuladoConcursoEspecial": 0.0,
    "valorAcumuladoProximoConcurso": 7095422.96,
    "valorEstimadoProximoConcurso": 7300000.0,
    "valorSaldoReservaGarantidora": 0.0,
    "valorTotalPremioFaixaUm": 0.0
  }
}