{
  "cookies": {
    "__uzmc": "80848560529026",
    "__uzmd": "1767320559"
  },
  "created_at": "2026-01-02T02:22:24.338281+00:00",
  "elapsed": 0.070997,
  "encoding": "utf-8",
  "expires": "2026-07-01T02:22:24.338264+00:00",
  "headers": {
    "Cache-Control": "no-cache",
    "Connection": "keep-alive",
    "Content-Encoding": "gzip",
    "Content-Type": "application/json",
    "Cross-Origin-Opener-Policy": "same-origin",
    "Date": "Fri, 02 Jan 2026 02:22:39 GMT",
    "Expires": "-1",
    "Pragma": "no-cache",
    "Set-Cookie": "__uzmc=80848560529026; HttpOnly; path=/; Expires=Fri, 03-Jul-26 02:22:39 GMT ; Max-Age=15724800; SameSite=Lax, __uzmd=1767320559; HttpOnly; path=/; Expires=Fri, 03-Jul-26 02:22:39 GMT ; Max-Age=15724800; SameSite=Lax",
    "Transfer-Encoding": "chunked",
    "Vary": "Accept-Encoding",
    "X-Azion-Edge-Location": "CGH",
    "X-Azion-Request-Id": "9a7445dcadabadb36888773dca7a4a18",
    "X-Content-Type-Options": "nosniff",
    "X-Frame-Options": "deny",
    "X-XSS-Protection": "1; mode=block",
    "xS": "051"
  },
  "reason": "OK",
  "request": {
    "body": "",
    "cookies": {
      "__uzma": "c737c81c-d39d-4da4-90e4-17345d3b452d",
      "__uzmb": "1767320398",
      "__uzme": "6012",
      "__uzmc": "82156560283124",
      "__uzmd": "1767320559"
    },
    "headers": {
      "Accept": "*/*",
      "Accept-Encoding": "gzip, deflate, zstd",
      "Connection": "keep-alive",
      "Cookie": "__uzma=c737c81c-d39d-4da4-90e4-17345d3b452d; __uzmb=1767320398; __uzme=6012; __uzmc=82156560283124; __uzmd=1767320559",
      "User-Agent": "python-requests/2.32.5"
    },
    "method": "GET",
    "url": "https://servicebus2.caixa.gov.br/portaldeloterias/api/lotofacil/1865"
  },
  "status_code": 200,
  "url": "https://servicebus2.caixa.gov.br/portaldeloterias/api/lotofacil/1865",
  "_decoded_content": {
    "acumulado": false,
    "dataApuracao": "16/09/2019",
    "dataProximoConcurso": "18/09/2019",
    "dezenasSorteadasOrdemSorteio": [
      "07",
      "02",
      "19",
      "21",
      "03",
      "12",
      "05",
      "14",
      "10",
      "20",
      "25",
      "17",
      "11",
      "06",
      "24"
    ],
    "exibirDetalhamentoPorCidade": true,
    "id": null,
    "indicadorConcursoEspecial": 1,
    "listaDezenas": [
      "02",
      "03",
      "05",
      "06",
      "07",
      "10",
      "11",
      "12",
      "14",
      "17",
      "19",
      "20",
      "21",
      "24",
      "25"
    ],
    "listaDezenasSegundoSorteio": null,
    "listaMunicipioUFGanhadores": [
      {
        "ganhadores": 1,
        "municipio": "GUANAMBI",
        "nomeFatansiaUL": "",
        "posicao": 1,
        "serie": "",
        "uf": "BA"
      },
      {
        "ganhadores": 1,
        "municipio": "IGUA\u00cd",
        "nomeFatansiaUL": "",
        "posicao": 1,
        "serie": "",
        "uf": "BA"
      },
      {
        "ganhadores": 1,
        "municipio": "CONTAGEM",
        "nomeFatansiaUL": "",
        "posicao": 1,
        "serie": "",
        "uf": "MG"
      },
      {
        "ganhadores": 1,
        "municipio": "CARLINDA",
        "nomeFatansiaUL": "",
        "posicao": 1,
        "serie": "",
        "uf": "MT"
      },
      {
        "ganhadores": 1,
        "municipio": "AMERICANA",
        "nomeFatansiaUL": "",
        "posicao": 1,
        "serie": "",
        "uf": "SP"
      },
      {
        "ganhadores": 1,
        "municipio": "FERNANDOPOLIS",
        "nomeFatansiaUL": "",
        "posicao": 1,
        "serie": "",
        "uf": "SP"
      },
      {
        "ganhadores": 1,
        "municipio": "Canal Eletr\u00f4nico",
        "nomeFatansiaUL": "",
        "posicao": 1,
        "serie": "",
        "uf": "XX"
      }
    ],
    "listaRateioPremio": [
      {
        "descricaoFaixa": "15 acertos",
        "faixa": 1,
        "numeroDeGanhadores": 7,
        "valorPremio": 309112.63
      },
      {
        "descricaoFaixa": "14 acertos",
        "faixa": 2,
        "numeroDeGanhadores": 1021,
        "valorPremio": 931.55
      },
      {
        "descricaoFaixa": "13 acertos",
        "faixa": 3,
        "numeroDeGanhadores": 24379,
        "valorPremio": 20.0
      },
      {
        "descricaoFaixa": "12 acertos",
        "faixa": 4,
        "numeroDeGanhadores": 248130,
        "valorPremio": 8.0
      },
      {
        "descricaoFaixa": "11 acertos",
        "faixa": 5,
        "numeroDeGanhadores": 1206000,
        "valorPremio": 4.0
      }
    ],
    "listaResultadoEquipeEsportiva": null,
    "localSorteio": "Espa\u00e7o Loterias Caixa",
    "nomeMunicipioUFSorteio": "S\u00c3O PAULO, SP",
    "nomeTimeCoracaoMesSorte": "",
    "numero": 1865,
    "numeroConcursoAnterior": 1864,
    "numeroConcursoFinal_0_5": 1870,
    "numeroConcursoProximo": 1866,
    "numeroJogo": 8,
    "observacao": "",
    "premiacaoContingencia": null,
    "tipoJogo": "LOTOFACIL",
    "tipoPublicacao": 3,
    "ultimoConcurso": true,
    "valorArrecadado": 27802534.0,
    "valorAcumuladoConcurso_0_5": 0.0,
    "valorAcumuladoConcursoEspecial": 2063732.65,
    "valorAcumuladoProximoConcurso": 0.0,
    "valorEstimadoProximoConcurso": 2000000.0,
    "valorSaldoReservaGarantidora": 0.0,
    "valorTotalPremioFaixaUm": 0.0
  }
}