{
  "cookies": {
    "__uzmc": "47089138427467",
    "__uzmd": "1782888290"
  },
  "created_at": "2026-07-01T06:44:50.714952+00:00",
  "elapsed": 0.220567,
  "encoding": "utf-8",
  "expires": "2026-12-28T06:44:50.714926+00:00",
  "headers": {
    "Cache-Control": "no-cache",
    "Connection": "keep-alive",
    "Content-Encoding": "gzip",
    "Content-Type": "application/json",
    "Cross-Origin-Opener-Policy": "same-origin",
    "Date": "Wed, 01 Jul 2026 06:44:50 GMT",
    "Expires": "-1",
    "Pragma": "no-cache",
    "Set-Cookie": "__uzmc=47089138427467; HttpOnly; path=/; Expires=Wed, 30-Dec-26 06:44:50 GMT ; Max-Age=15724800; SameSite=Lax, __uzmd=1782888290; HttpOnly; path=/; Expires=Wed, 30-Dec-26 06:44:50 GMT ; Max-Age=15724800; SameSite=Lax",
    "Transfer-Encoding": "chunked",
    "Vary": "Accept-Encoding",
    "X-Azion-Edge-Location": "LAX",
    "X-Azion-Request-Id": "0c030a7134e7b2cf8f41b421900b005a",
    "X-Content-Type-Options": "nosniff",
    "X-Frame-Options": "deny",
    "X-XSS-Protection": "1; mode=block",
    "xS": "005c"
  },
  "reason": "OK",
  "request": {
    "cookies": {
      "__uzma": "21af2338-6d0e-4dd8-8b8c-bc53ba949958",
      "__uzmb": "1782888184",
      "__uzme": "0892",
      "__uzmc": "23734138154381",
      "__uzmd": "1782888290"
    },
    "headers": {
      "Accept": "*/*",
      "Accept-Encoding": "gzip, deflate, zstd",
      "Connection": "keep-alive",
      "Cookie": "__uzma=21af2338-6d0e-4dd8-8b8c-bc53ba949958; __uzmb=1782888184; __uzme=0892; __uzmc=23734138154381; __uzmd=1782888290",
      "User-Agent": "python-requests/2.34.2"
    },
    "method": "GET",
    "url": "https://servicebus2.caixa.gov.br/portaldeloterias/api/quina/458"
  },
  "status_code": 200,
  "url": "https://servicebus2.caixa.gov.br/portaldeloterias/api/quina/458",
  "_decoded_content": {
    "acumulado": false,
    "dataApuracao": "24/09/1998",
    "dataProximoConcurso": "",
    "dezenasSorteadasOrdemSorteio": [
      "73",
      "29",
      "62",
      "21",
      "40"
    ],
    "exibirDetalhamentoPorCidade": true,
    "id": null,
    "indicadorConcursoEspecial": 1,
    "listaDezenas": [
      "21",
      "29",
      "40",
      "62",
      "73"
    ],
    "listaDezenasSegundoSorteio": null,
    "listaMunicipioUFGanhadores": [],
    "listaRateioPremio": [
      {
        "descricaoFaixa": "5 acertos",
        "faixa": 1,
        "numeroDeGanhadores": 1,
        "valorPremio": 256230.58
      },
      {
        "descricaoFaixa": "4 acertos",
        "faixa": 2,
        "numeroDeGanhadores": 103,
        "valorPremio": 2487.68
      },
      {
        "descricaoFaixa": "3 acertos",
        "faixa": 3,
        "numeroDeGanhadores": 6406,
        "valorPremio": 53.23
      }
    ],
    "listaResultadoEquipeEsportiva": null,
    "localSorteio": "",
    "nomeMunicipioUFSorteio": "",
    "nomeTimeCoracaoMesSorte": "",
    "numero": 458,
    "numeroConcursoAnterior": 457,
    "numeroConcursoFinal_0_5": 465,
    "numeroConcursoProximo": 459,
    "numeroJogo": 3,
    "observacao": "Ganhador da QUINA do Estado da Bahia.",
    "premiacaoContingencia": null,
    "tipoJogo": "QUINA",
    "tipoPublicacao": 3,
    "ultimoConcurso": true,
    "valorArrecadado": 0.0,
    "valorAcumuladoConcurso_0_5": 0.0,
    "valorAcumuladoConcursoEspecial": 0.0,
    "valorAcumuladoProximoConcurso": 0.0,
    "valorEstimadoProximoConcurso": 0.0,
    "valorSaldoReservaGarantidora": 0.0,
    "valorTotalPremioFaixaUm": 0.0
  }
}