{
  "cookies": {
    "__uzmc": "55037378794301",
    "__uzmd": "1767321472"
  },
  "created_at": "2026-01-02T02:37:37.379410+00:00",
  "elapsed": 0.081517,
  "encoding": "utf-8",
  "expires": "2026-07-01T02:37:37.379393+00:00",
  "headers": {
    "Cache-Control": "no-cache",
    "Connection": "keep-alive",
    "Content-Encoding": "gzip",
    "Content-Type": "application/json",
    "Cross-Origin-Opener-Policy": "same-origin",
    "Date": "Fri, 02 Jan 2026 02:37:52 GMT",
    "Expires": "-1",
    "Pragma": "no-cache",
    "Set-Cookie": "__uzmc=55037378794301; HttpOnly; path=/; Expires=Fri, 03-Jul-26 02:37:52 GMT ; Max-Age=15724800; SameSite=Lax, __uzmd=1767321472; HttpOnly; path=/; Expires=Fri, 03-Jul-26 02:37:52 GMT ; Max-Age=15724800; SameSite=Lax",
    "Transfer-Encoding": "chunked",
    "Vary": "Accept-Encoding",
    "X-Azion-Edge-Location": "CGH",
    "X-Azion-Request-Id": "21d3c4d20a0b1d212cbba051fa8fbd17",
    "X-Content-Type-Options": "nosniff",
    "X-Frame-Options": "deny",
    "X-XSS-Protection": "1; mode=block",
    "xS": "051"
  },
  "reason": "OK",
  "request": {
    "body": "",
    "cookies": {
      "__uzma": "5a09f817-fac9-4be5-a3e1-c2205b115e1d",
      "__uzmb": "1767321326",
      "__uzme": "3767",
      "__uzmc": "40587378454008",
      "__uzmd": "1767321472"
    },
    "headers": {
      "Accept": "*/*",
      "Accept-Encoding": "gzip, deflate, zstd",
      "Connection": "keep-alive",
      "Cookie": "__uzma=5a09f817-fac9-4be5-a3e1-c2205b115e1d; __uzmb=1767321326; __uzme=3767; __uzmc=40587378454008; __uzmd=1767321472",
      "User-Agent": "python-requests/2.32.5"
    },
    "method": "GET",
    "url": "https://servicebus2.caixa.gov.br/portaldeloterias/api/quina/1259"
  },
  "status_code": 200,
  "url": "https://servicebus2.caixa.gov.br/portaldeloterias/api/quina/1259",
  "_decoded_content": {
    "acumulado": true,
    "dataApuracao": "07/02/2004",
    "dataProximoConcurso": "10/02/2004",
    "dezenasSorteadasOrdemSorteio": [
      "38",
      "46",
      "14",
      "50",
      "16"
    ],
    "exibirDetalhamentoPorCidade": true,
    "id": null,
    "indicadorConcursoEspecial": 1,
    "listaDezenas": [
      "14",
      "16",
      "38",
      "46",
      "50"
    ],
    "listaDezenasSegundoSorteio": null,
    "listaMunicipioUFGanhadores": [],
    "listaRateioPremio": [
      {
        "descricaoFaixa": "5 acertos",
        "faixa": 1,
        "numeroDeGanhadores": 0,
        "valorPremio": 0.0
      },
      {
        "descricaoFaixa": "4 acertos",
        "faixa": 2,
        "numeroDeGanhadores": 144,
        "valorPremio": 2371.1
      },
      {
        "descricaoFaixa": "3 acertos",
        "faixa": 3,
        "numeroDeGanhadores": 7795,
        "valorPremio": 58.19
      }
    ],
    "listaResultadoEquipeEsportiva": null,
    "localSorteio": "Caminh\u00e3o da Sorte",
    "nomeMunicipioUFSorteio": "VACARIA, RS",
    "nomeTimeCoracaoMesSorte": "",
    "numero": 1259,
    "numeroConcursoAnterior": 1258,
    "numeroConcursoFinal_0_5": 1265,
    "numeroConcursoProximo": 1260,
    "numeroJogo": 3,
    "observacao": "ACUMULOU!!! Estimativa de pr\u00eamio (QUINA) pr\u00f3ximo concurso: R$700.000,00 (SETECENTOS MIL REAIS).",
    "premiacaoContingencia": null,
    "tipoJogo": "QUINA",
    "tipoPublicacao": 3,
    "ultimoConcurso": true,
    "valorArrecadado": 0.0,
    "valorAcumuladoConcurso_0_5": 0.0,
    "valorAcumuladoConcursoEspecial": 0.0,
    "valorAcumuladoProximoConcurso": 341438.33,
    "valorEstimadoProximoConcurso": 0.0,
    "valorSaldoReservaGarantidora": 0.0,
    "valorTotalPremioFaixaUm": 0.0
  }
}