{
  "cookies": {
    "__uzmc": "38488763051266",
    "__uzmd": "1782883993"
  },
  "created_at": "2026-07-01T05:33:14.120499+00:00",
  "elapsed": 0.295163,
  "encoding": "utf-8",
  "expires": "2026-12-28T05:33:14.120473+00:00",
  "headers": {
    "Cache-Control": "no-cache",
    "Connection": "keep-alive",
    "Content-Encoding": "gzip",
    "Content-Type": "application/json",
    "Cross-Origin-Opener-Policy": "same-origin",
    "Date": "Wed, 01 Jul 2026 05:33:14 GMT",
    "Expires": "-1",
    "Pragma": "no-cache",
    "Set-Cookie": "__uzmc=38488763051266; HttpOnly; path=/; Expires=Wed, 30-Dec-26 05:33:13 GMT ; Max-Age=15724800; SameSite=Lax, __uzmd=1782883993; HttpOnly; path=/; Expires=Wed, 30-Dec-26 05:33:13 GMT ; Max-Age=15724800; SameSite=Lax",
    "Transfer-Encoding": "chunked",
    "Vary": "Accept-Encoding",
    "X-Azion-Edge-Location": "SJC",
    "X-Azion-Request-Id": "8c71a72d0067fdd6388b07bc1aee7b7c",
    "X-Content-Type-Options": "nosniff",
    "X-Frame-Options": "deny",
    "X-XSS-Protection": "1; mode=block",
    "xS": "051m"
  },
  "reason": "OK",
  "request": {
    "cookies": {
      "__uzma": "b7c09776-b542-4931-b36b-51a1d43d6271",
      "__uzmb": "1782883209",
      "__uzme": "0415",
      "__uzmc": "93253762774679",
      "__uzmd": "1782883993"
    },
    "headers": {
      "Accept": "*/*",
      "Accept-Encoding": "gzip, deflate, zstd",
      "Connection": "keep-alive",
      "Cookie": "__uzma=b7c09776-b542-4931-b36b-51a1d43d6271; __uzmb=1782883209; __uzme=0415; __uzmc=93253762774679; __uzmd=1782883993",
      "User-Agent": "python-requests/2.34.2"
    },
    "method": "GET",
    "url": "https://servicebus2.caixa.gov.br/portaldeloterias/api/duplasena/2540"
  },
  "status_code": 200,
  "url": "https://servicebus2.caixa.gov.br/portaldeloterias/api/duplasena/2540",
  "_decoded_content": {
    "acumulado": true,
    "dataApuracao": "13/07/2023",
    "dataProximoConcurso": "15/07/2023",
    "dezenasSorteadasOrdemSorteio": [
      "29",
      "24",
      "15",
      "05",
      "13",
      "19",
      "04",
      "37",
      "19",
      "11",
      "13",
      "39"
    ],
    "exibirDetalhamentoPorCidade": true,
    "id": null,
    "indicadorConcursoEspecial": 1,
    "listaDezenas": [
      "05",
      "13",
      "15",
      "19",
      "24",
      "29"
    ],
    "listaDezenasSegundoSorteio": [
      "04",
      "11",
      "13",
      "19",
      "37",
      "39"
    ],
    "listaMunicipioUFGanhadores": [],
    "listaRateioPremio": [
      {
        "descricaoFaixa": "6 acertos",
        "faixa": 1,
        "numeroDeGanhadores": 0,
        "valorPremio": 0.0
      },
      {
        "descricaoFaixa": "5 acertos",
        "faixa": 2,
        "numeroDeGanhadores": 19,
        "valorPremio": 3119.09
      },
      {
        "descricaoFaixa": "4 acertos",
        "faixa": 3,
        "numeroDeGanhadores": 882,
        "valorPremio": 76.79
      },
      {
        "descricaoFaixa": "3 acertos",
        "faixa": 4,
        "numeroDeGanhadores": 15562,
        "valorPremio": 2.17
      },
      {
        "descricaoFaixa": "6 acertos",
        "faixa": 5,
        "numeroDeGanhadores": 0,
        "valorPremio": 0.0
      },
      {
        "descricaoFaixa": "5 acertos",
        "faixa": 6,
        "numeroDeGanhadores": 16,
        "valorPremio": 3333.53
      },
      {
        "descricaoFaixa": "4 acertos",
        "faixa": 7,
        "numeroDeGanhadores": 726,
        "valorPremio": 93.29
      },
      {
        "descricaoFaixa": "3 acertos",
        "faixa": 8,
        "numeroDeGanhadores": 14323,
        "valorPremio": 2.36
      }
    ],
    "listaResultadoEquipeEsportiva": null,
    "localSorteio": "ESPA\u00c7O DA SORTE",
    "nomeMunicipioUFSorteio": "S\u00c3O PAULO, SP",
    "nomeTimeCoracaoMesSorte": "\u0000\u0000\u0000\u0000\u0000\u0000\u0000\u0000\u0000\u0000\u0000\u0000\u0000\u0000\u0000\u0000\u0000",
    "numero": 2540,
    "numeroConcursoAnterior": 2539,
    "numeroConcursoFinal_0_5": 0,
    "numeroConcursoProximo": 2541,
    "numeroJogo": 18,
    "observacao": "",
    "premiacaoContingencia": null,
    "tipoJogo": "DUPLA_SENA",
    "tipoPublicacao": 3,
    "ultimoConcurso": true,
    "valorArrecadado": 1952965.0,
    "valorAcumuladoConcurso_0_5": 0.0,
    "valorAcumuladoConcursoEspecial": 4220182.46,
    "valorAcumuladoProximoConcurso": 2687149.32,
    "valorEstimadoProximoConcurso": 3000000.0,
    "valorSaldoReservaGarantidora": 0.0,
    "valorTotalPremioFaixaUm": 0.0
  }
}