{
  "cookies": {
    "__uzmc": "63747468112389",
    "__uzmd": "1782886909"
  },
  "created_at": "2026-07-01T06:21:50.074051+00:00",
  "elapsed": 0.223351,
  "encoding": "utf-8",
  "expires": "2026-12-28T06:21:50.074025+00:00",
  "headers": {
    "Cache-Control": "no-cache",
    "Connection": "keep-alive",
    "Content-Encoding": "gzip",
    "Content-Type": "application/json",
    "Cross-Origin-Opener-Policy": "same-origin",
    "Date": "Wed, 01 Jul 2026 06:21:50 GMT",
    "Expires": "-1",
    "Pragma": "no-cache",
    "Set-Cookie": "__uzmc=63747468112389; HttpOnly; path=/; Expires=Wed, 30-Dec-26 06:21:49 GMT ; Max-Age=15724800; SameSite=Lax, __uzmd=1782886909; HttpOnly; path=/; Expires=Wed, 30-Dec-26 06:21:49 GMT ; Max-Age=15724800; SameSite=Lax",
    "Transfer-Encoding": "chunked",
    "Vary": "Accept-Encoding",
    "X-Azion-Edge-Location": "LAX",
    "X-Azion-Request-Id": "040d53f2c5d5f2a185f07bcaec8c1484",
    "X-Content-Type-Options": "nosniff",
    "X-Frame-Options": "deny",
    "X-XSS-Protection": "1; mode=block",
    "xS": "054"
  },
  "reason": "OK",
  "request": {
    "cookies": {
      "__uzma": "a1a48d41-36ee-4fb0-8f61-7e7e81184436",
      "__uzmb": "1782886526",
      "__uzme": "6385",
      "__uzmc": "59888467861166",
      "__uzmd": "1782886909"
    },
    "headers": {
      "Accept": "*/*",
      "Accept-Encoding": "gzip, deflate, zstd",
      "Connection": "keep-alive",
      "Cookie": "__uzma=a1a48d41-36ee-4fb0-8f61-7e7e81184436; __uzmb=1782886526; __uzme=6385; __uzmc=59888467861166; __uzmd=1782886909",
      "User-Agent": "python-requests/2.34.2"
    },
    "method": "GET",
    "url": "https://servicebus2.caixa.gov.br/portaldeloterias/api/lotomania/1557"
  },
  "status_code": 200,
  "url": "https://servicebus2.caixa.gov.br/portaldeloterias/api/lotomania/1557",
  "_decoded_content": {
    "acumulado": true,
    "dataApuracao": "23/05/2015",
    "dataProximoConcurso": "27/05/2015",
    "dezenasSorteadasOrdemSorteio": [
      "80",
      "33",
      "95",
      "36",
      "17",
      "42",
      "13",
      "06",
      "47",
      "02",
      "29",
      "08",
      "57",
      "49",
      "00",
      "67",
      "91",
      "40",
      "23",
      "75"
    ],
    "exibirDetalhamentoPorCidade": true,
    "id": null,
    "indicadorConcursoEspecial": 1,
    "listaDezenas": [
      "00",
      "02",
      "06",
      "08",
      "13",
      "17",
      "23",
      "29",
      "33",
      "36",
      "40",
      "42",
      "47",
      "49",
      "57",
      "67",
      "75",
      "80",
      "91",
      "95"
    ],
    "listaDezenasSegundoSorteio": null,
    "listaMunicipioUFGanhadores": [
      {
        "ganhadores": 1,
        "municipio": "DOURADOS",
        "nomeFatansiaUL": "",
        "posicao": 2,
        "serie": "",
        "uf": "MS"
      }
    ],
    "listaRateioPremio": [
      {
        "descricaoFaixa": "20 acertos",
        "faixa": 1,
        "numeroDeGanhadores": 0,
        "valorPremio": 0.0
      },
      {
        "descricaoFaixa": "19 acertos",
        "faixa": 2,
        "numeroDeGanhadores": 17,
        "valorPremio": 20786.95
      },
      {
        "descricaoFaixa": "18 acertos",
        "faixa": 3,
        "numeroDeGanhadores": 237,
        "valorPremio": 1491.05
      },
      {
        "descricaoFaixa": "17 acertos",
        "faixa": 4,
        "numeroDeGanhadores": 1901,
        "valorPremio": 116.18
      },
      {
        "descricaoFaixa": "16 acertos",
        "faixa": 5,
        "numeroDeGanhadores": 10804,
        "valorPremio": 20.44
      },
      {
        "descricaoFaixa": "0 acertos",
        "faixa": 6,
        "numeroDeGanhadores": 1,
        "valorPremio": 176689.07
      }
    ],
    "listaResultadoEquipeEsportiva": null,
    "localSorteio": "CAMINH\u00c3O DA SORTE",
    "nomeMunicipioUFSorteio": "IPOR\u00c1, GO",
    "nomeTimeCoracaoMesSorte": "",
    "numero": 1557,
    "numeroConcursoAnterior": 1556,
    "numeroConcursoFinal_0_5": 0,
    "numeroConcursoProximo": 1558,
    "numeroJogo": 16,
    "observacao": "",
    "premiacaoContingencia": null,
    "tipoJogo": "LOTOMANIA",
    "tipoPublicacao": 3,
    "ultimoConcurso": true,
    "valorArrecadado": 7167705.0,
    "valorAcumuladoConcurso_0_5": 0.0,
    "valorAcumuladoConcursoEspecial": 4400381.49,
    "valorAcumuladoProximoConcurso": 4762904.93,
    "valorEstimadoProximoConcurso": 5200000.0,
    "valorSaldoReservaGarantidora": 0.0,
    "valorTotalPremioFaixaUm": 0.0
  }
}