{
  "cookies": {
    "__uzmc": "57517214015922",
    "__uzmd": "1767320817"
  },
  "created_at": "2026-01-02T02:26:42.604460+00:00",
  "elapsed": 0.085315,
  "encoding": "utf-8",
  "expires": "2026-07-01T02:26:42.604440+00:00",
  "headers": {
    "Cache-Control": "no-cache",
    "Connection": "keep-alive",
    "Content-Encoding": "gzip",
    "Content-Type": "application/json",
    "Cross-Origin-Opener-Policy": "same-origin",
    "Date": "Fri, 02 Jan 2026 02:26:57 GMT",
    "Expires": "-1",
    "Pragma": "no-cache",
    "Set-Cookie": "__uzmc=57517214015922; HttpOnly; path=/; Expires=Fri, 03-Jul-26 02:26:57 GMT ; Max-Age=15724800; SameSite=Lax, __uzmd=1767320817; HttpOnly; path=/; Expires=Fri, 03-Jul-26 02:26:57 GMT ; Max-Age=15724800; SameSite=Lax",
    "Transfer-Encoding": "chunked",
    "Vary": "Accept-Encoding",
    "X-Azion-Edge-Location": "CGH",
    "X-Azion-Request-Id": "84f1525227d4501441631b0186fb6e31",
    "X-Content-Type-Options": "nosniff",
    "X-Frame-Options": "deny",
    "X-XSS-Protection": "1; mode=block",
    "xS": "051"
  },
  "reason": "OK",
  "request": {
    "body": "",
    "cookies": {
      "__uzma": "875a53ae-d886-4172-a23f-9b5de662a103",
      "__uzmb": "1767320749",
      "__uzme": "4799",
      "__uzmc": "55106213723938",
      "__uzmd": "1767320817"
    },
    "headers": {
      "Accept": "*/*",
      "Accept-Encoding": "gzip, deflate, zstd",
      "Connection": "keep-alive",
      "Cookie": "__uzma=875a53ae-d886-4172-a23f-9b5de662a103; __uzmb=1767320749; __uzme=4799; __uzmc=55106213723938; __uzmd=1767320817",
      "User-Agent": "python-requests/2.32.5"
    },
    "method": "GET",
    "url": "https://servicebus2.caixa.gov.br/portaldeloterias/api/lotomania/710"
  },
  "status_code": 200,
  "url": "https://servicebus2.caixa.gov.br/portaldeloterias/api/lotomania/710",
  "_decoded_content": {
    "acumulado": true,
    "dataApuracao": "31/03/2007",
    "dataProximoConcurso": "04/04/2007",
    "dezenasSorteadasOrdemSorteio": [
      "66",
      "60",
      "58",
      "75",
      "38",
      "24",
      "46",
      "96",
      "62",
      "69",
      "72",
      "06",
      "03",
      "95",
      "52",
      "18",
      "42",
      "28",
      "59",
      "50"
    ],
    "exibirDetalhamentoPorCidade": true,
    "id": null,
    "indicadorConcursoEspecial": 1,
    "listaDezenas": [
      "03",
      "06",
      "18",
      "24",
      "28",
      "38",
      "42",
      "46",
      "50",
      "52",
      "58",
      "59",
      "60",
      "62",
      "66",
      "69",
      "72",
      "75",
      "95",
      "96"
    ],
    "listaDezenasSegundoSorteio": null,
    "listaMunicipioUFGanhadores": [],
    "listaRateioPremio": [
      {
        "descricaoFaixa": "20 acertos",
        "faixa": 1,
        "numeroDeGanhadores": 0,
        "valorPremio": 0.0
      },
      {
        "descricaoFaixa": "19 acertos",
        "faixa": 2,
        "numeroDeGanhadores": 11,
        "valorPremio": 23619.47
      },
      {
        "descricaoFaixa": "18 acertos",
        "faixa": 3,
        "numeroDeGanhadores": 180,
        "valorPremio": 1443.41
      },
      {
        "descricaoFaixa": "17 acertos",
        "faixa": 4,
        "numeroDeGanhadores": 1459,
        "valorPremio": 88.71
      },
      {
        "descricaoFaixa": "16 acertos",
        "faixa": 5,
        "numeroDeGanhadores": 9246,
        "valorPremio": 14.0
      },
      {
        "descricaoFaixa": "0 acertos",
        "faixa": 6,
        "numeroDeGanhadores": 0,
        "valorPremio": 0.0
      }
    ],
    "listaResultadoEquipeEsportiva": null,
    "localSorteio": "Caminh\u00e3o da Sorte",
    "nomeMunicipioUFSorteio": "UBERL\u00c2NDIA, MG",
    "nomeTimeCoracaoMesSorte": "",
    "numero": 710,
    "numeroConcursoAnterior": 709,
    "numeroConcursoFinal_0_5": 0,
    "numeroConcursoProximo": 711,
    "numeroJogo": 16,
    "observacao": "ACUMULOU!!! Estimativa de pr\u00eamio (20 acertos) para o pr\u00f3ximo concurso a ser realizado em 04/04/2007: R$2.200.000,00.",
    "premiacaoContingencia": null,
    "tipoJogo": "LOTOMANIA",
    "tipoPublicacao": 3,
    "ultimoConcurso": true,
    "valorArrecadado": 0.0,
    "valorAcumuladoConcurso_0_5": 0.0,
    "valorAcumuladoConcursoEspecial": 0.0,
    "valorAcumuladoProximoConcurso": 1779479.2,
    "valorEstimadoProximoConcurso": 0.0,
    "valorSaldoReservaGarantidora": 0.0,
    "valorTotalPremioFaixaUm": 0.0
  }
}