{
  "cookies": {
    "__uzmc": "69103640093272",
    "__uzmd": "1782887973"
  },
  "created_at": "2026-07-01T06:39:33.357144+00:00",
  "elapsed": 0.220709,
  "encoding": "utf-8",
  "expires": "2026-12-28T06:39:33.357116+00:00",
  "headers": {
    "Cache-Control": "no-cache",
    "Connection": "keep-alive",
    "Content-Encoding": "gzip",
    "Content-Type": "application/json",
    "Cross-Origin-Opener-Policy": "same-origin",
    "Date": "Wed, 01 Jul 2026 06:39:33 GMT",
    "Expires": "-1",
    "Pragma": "no-cache",
    "Set-Cookie": "__uzmc=69103640093272; HttpOnly; path=/; Expires=Wed, 30-Dec-26 06:39:33 GMT ; Max-Age=15724800; SameSite=Lax, __uzmd=1782887973; HttpOnly; path=/; Expires=Wed, 30-Dec-26 06:39:33 GMT ; Max-Age=15724800; SameSite=Lax",
    "Transfer-Encoding": "chunked",
    "Vary": "Accept-Encoding",
    "X-Azion-Edge-Location": "LAX",
    "X-Azion-Request-Id": "8d0a98b58e6c10c514e4148bf9565d2f",
    "X-Content-Type-Options": "nosniff",
    "X-Frame-Options": "deny",
    "X-XSS-Protection": "1; mode=block",
    "xS": "054"
  },
  "reason": "OK",
  "request": {
    "cookies": {
      "__uzma": "b9c5fdee-a82a-41cc-95a9-4337405e0c93",
      "__uzmb": "1782887324",
      "__uzme": "0559",
      "__uzmc": "61235639766312",
      "__uzmd": "1782887972"
    },
    "headers": {
      "Accept": "*/*",
      "Accept-Encoding": "gzip, deflate, zstd",
      "Connection": "keep-alive",
      "Cookie": "__uzma=b9c5fdee-a82a-41cc-95a9-4337405e0c93; __uzmb=1782887324; __uzme=0559; __uzmc=61235639766312; __uzmd=1782887972",
      "User-Agent": "python-requests/2.34.2"
    },
    "method": "GET",
    "url": "https://servicebus2.caixa.gov.br/portaldeloterias/api/megasena/2130"
  },
  "status_code": 200,
  "url": "https://servicebus2.caixa.gov.br/portaldeloterias/api/megasena/2130",
  "_decoded_content": {
    "acumulado": true,
    "dataApuracao": "02/03/2019",
    "dataProximoConcurso": "06/03/2019",
    "dezenasSorteadasOrdemSorteio": [
      "13",
      "53",
      "16",
      "36",
      "55",
      "54"
    ],
    "exibirDetalhamentoPorCidade": true,
    "id": null,
    "indicadorConcursoEspecial": 1,
    "listaDezenas": [
      "13",
      "16",
      "36",
      "53",
      "54",
      "55"
    ],
    "listaDezenasSegundoSorteio": null,
    "listaMunicipioUFGanhadores": [],
    "listaRateioPremio": [
      {
        "descricaoFaixa": "6 acertos",
        "faixa": 1,
        "numeroDeGanhadores": 0,
        "valorPremio": 0.0
      },
      {
        "descricaoFaixa": "5 acertos",
        "faixa": 2,
        "numeroDeGanhadores": 101,
        "valorPremio": 42283.94
      },
      {
        "descricaoFaixa": "4 acertos",
        "faixa": 3,
        "numeroDeGanhadores": 7900,
        "valorPremio": 772.27
      }
    ],
    "listaResultadoEquipeEsportiva": null,
    "localSorteio": "CAMINH\u00c3O DA SORTE",
    "nomeMunicipioUFSorteio": "VIDEIRA, SC",
    "nomeTimeCoracaoMesSorte": "",
    "numero": 2130,
    "numeroConcursoAnterior": 2129,
    "numeroConcursoFinal_0_5": 2135,
    "numeroConcursoProximo": 2131,
    "numeroJogo": 2,
    "observacao": "",
    "premiacaoContingencia": null,
    "tipoJogo": "MEGA_SENA",
    "tipoPublicacao": 3,
    "ultimoConcurso": true,
    "valorArrecadado": 74073569.5,
    "valorAcumuladoConcurso_0_5": 4944995.55,
    "valorAcumuladoConcursoEspecial": 12222216.77,
    "valorAcumuladoProximoConcurso": 71818978.53,
    "valorEstimadoProximoConcurso": 80000000.0,
    "valorSaldoReservaGarantidora": 0.0,
    "valorTotalPremioFaixaUm": 0.0
  }
}