{
  "cookies": {
    "__uzmc": "44485822716055",
    "__uzmd": "1767321291"
  },
  "created_at": "2026-01-02T02:34:36.327653+00:00",
  "elapsed": 0.141435,
  "encoding": "utf-8",
  "expires": "2026-07-01T02:34:36.327636+00:00",
  "headers": {
    "Cache-Control": "no-cache",
    "Connection": "keep-alive",
    "Content-Encoding": "gzip",
    "Content-Type": "application/json",
    "Cross-Origin-Opener-Policy": "same-origin",
    "Date": "Fri, 02 Jan 2026 02:34:51 GMT",
    "Expires": "-1",
    "Pragma": "no-cache",
    "Set-Cookie": "__uzmc=44485822716055; HttpOnly; path=/; Expires=Fri, 03-Jul-26 02:34:51 GMT ; Max-Age=15724800; SameSite=Lax, __uzmd=1767321291; HttpOnly; path=/; Expires=Fri, 03-Jul-26 02:34:51 GMT ; Max-Age=15724800; SameSite=Lax",
    "Transfer-Encoding": "chunked",
    "Vary": "Accept-Encoding",
    "X-Azion-Edge-Location": "CGH",
    "X-Azion-Request-Id": "93b9abc831617a66f0a2912e5fccf08f",
    "X-Content-Type-Options": "nosniff",
    "X-Frame-Options": "deny",
    "X-XSS-Protection": "1; mode=block",
    "xS": "006c"
  },
  "reason": "OK",
  "request": {
    "body": "",
    "cookies": {
      "__uzma": "c49d0ed2-1a01-4295-97de-9262da9ecef9",
      "__uzmb": "1767321014",
      "__uzme": "4414",
      "__uzmc": "30274822446488",
      "__uzmd": "1767321290"
    },
    "headers": {
      "Accept": "*/*",
      "Accept-Encoding": "gzip, deflate, zstd",
      "Connection": "keep-alive",
      "Cookie": "__uzma=c49d0ed2-1a01-4295-97de-9262da9ecef9; __uzmb=1767321014; __uzme=4414; __uzmc=30274822446488; __uzmd=1767321290",
      "User-Agent": "python-requests/2.32.5"
    },
    "method": "GET",
    "url": "https://servicebus2.caixa.gov.br/portaldeloterias/api/megasena/2739"
  },
  "status_code": 200,
  "url": "https://servicebus2.caixa.gov.br/portaldeloterias/api/megasena/2739",
  "_decoded_content": {
    "acumulado": true,
    "dataApuracao": "20/06/2024",
    "dataProximoConcurso": "22/06/2024",
    "dezenasSorteadasOrdemSorteio": [
      "53",
      "25",
      "19",
      "45",
      "47",
      "37"
    ],
    "exibirDetalhamentoPorCidade": true,
    "id": null,
    "indicadorConcursoEspecial": 1,
    "listaDezenas": [
      "19",
      "25",
      "37",
      "45",
      "47",
      "53"
    ],
    "listaDezenasSegundoSorteio": null,
    "listaMunicipioUFGanhadores": [],
    "listaRateioPremio": [
      {
        "descricaoFaixa": "6 acertos",
        "faixa": 1,
        "numeroDeGanhadores": 0,
        "valorPremio": 0.0
      },
      {
        "descricaoFaixa": "5 acertos",
        "faixa": 2,
        "numeroDeGanhadores": 79,
        "valorPremio": 40920.93
      },
      {
        "descricaoFaixa": "4 acertos",
        "faixa": 3,
        "numeroDeGanhadores": 4990,
        "valorPremio": 925.49
      }
    ],
    "listaResultadoEquipeEsportiva": null,
    "localSorteio": "ESPA\u00c7O DA SORTE",
    "nomeMunicipioUFSorteio": "S\u00c3O PAULO,   SP",
    "nomeTimeCoracaoMesSorte": "\u0000\u0000\u0000\u0000\u0000\u0000\u0000\u0000\u0000\u0000\u0000\u0000\u0000\u0000\u0000\u0000\u0000",
    "numero": 2739,
    "numeroConcursoAnterior": 2738,
    "numeroConcursoFinal_0_5": 2740,
    "numeroConcursoProximo": 2740,
    "numeroJogo": 2,
    "observacao": "",
    "premiacaoContingencia": null,
    "tipoJogo": "MEGA_SENA",
    "tipoPublicacao": 3,
    "ultimoConcurso": true,
    "valorArrecadado": 56070170.0,
    "valorAcumuladoConcurso_0_5": 76588962.21,
    "valorAcumuladoConcursoEspecial": 67648340.43,
    "valorAcumuladoProximoConcurso": 76588962.21,
    "valorEstimadoProximoConcurso": 86000000.0,
    "valorSaldoReservaGarantidora": 0.0,
    "valorTotalPremioFaixaUm": 0.0
  }
}